streamlit_chroma_connection/__init__.py
streamlit_chroma_connection/chroma_connection.py
streamlit_chroma_connection-1.1.dist-info/LICENSE
streamlit_chroma_connection-1.1.dist-info/METADATA
streamlit_chroma_connection-1.1.dist-info/WHEEL
streamlit_chroma_connection-1.1.dist-info/top_level.txt
streamlit_chroma_connection-1.1.dist-info/RECORD
