Metadata-Version: 2.1
Name: streamlit-chroma-connection
Version: 1.1
Summary: A streamlit connection for Chroma vectorstore
Author-email: Pedro Toledo <pedroltoledo@gmail.com>
License: Apache License
Keywords: streamlit,connections,vectorstore,chroma
Classifier: License :: OSI Approved :: Apache Software License
Classifier: Programming Language :: Python
Classifier: Programming Language :: Python :: 3
Classifier: Programming Language :: Python :: 3.10
Requires-Python: >=3.10
License-File: LICENSE
Requires-Dist: streamlit <2.0.0,>=1.28.0
Requires-Dist: chromadb ==0.4.2
Requires-Dist: pandas <2.1.0,>=2.0.0
Requires-Dist: pysqlite3-binary ==0.5.0
Requires-Dist: langchain ==0.0.240
Provides-Extra: dev
Requires-Dist: flake8 ; extra == 'dev'
Requires-Dist: pre-commit ; extra == 'dev'
Requires-Dist: ipykernel ; extra == 'dev'
